openfl/__init__.py
openfl/__version__.py
openfl/component/__init__.py
openfl/component/aggregator/__init__.py
openfl/component/aggregator/aggregator.py
openfl/component/assigner/__init__.py
openfl/component/assigner/assigner.py
openfl/component/assigner/custom_assigner.py
openfl/component/assigner/random_grouped_assigner.py
openfl/component/assigner/static_grouped_assigner.py
openfl/component/assigner/tasks.py
openfl/component/ca/__init__.py
openfl/component/ca/ca.py
openfl/component/collaborator/__init__.py
openfl/component/collaborator/collaborator.py
openfl/component/director/__init__.py
openfl/component/director/director.py
openfl/component/director/experiment.py
openfl/component/envoy/__init__.py
openfl/component/envoy/envoy.py
openfl/component/straggler_handling_functions/__init__.py
openfl/component/straggler_handling_functions/cutoff_time_based_straggler_handling.py
openfl/component/straggler_handling_functions/percentage_based_straggler_handling.py
openfl/component/straggler_handling_functions/straggler_handling_function.py
openfl/cryptography/__init__.py
openfl/cryptography/ca.py
openfl/cryptography/io.py
openfl/cryptography/participant.py
openfl/databases/__init__.py
openfl/databases/tensor_db.py
openfl/databases/utilities/__init__.py
openfl/databases/utilities/dataframe.py
openfl/federated/__init__.py
openfl/federated/data/__init__.py
openfl/federated/data/federated_data.py
openfl/federated/data/loader.py
openfl/federated/data/loader_fe.py
openfl/federated/data/loader_fets_challenge.py
openfl/federated/data/loader_keras.py
openfl/federated/data/loader_pt.py
openfl/federated/data/loader_tf.py
openfl/federated/plan/__init__.py
openfl/federated/plan/plan.py
openfl/federated/task/__init__.py
openfl/federated/task/fl_model.py
openfl/federated/task/runner.py
openfl/federated/task/runner_fe.py
openfl/federated/task/runner_fets_challenge.py
openfl/federated/task/runner_keras.py
openfl/federated/task/runner_pt.py
openfl/federated/task/runner_tf.py
openfl_riscv-1.4.0.dev1.dist-info/LICENSE
openfl_riscv-1.4.0.dev1.dist-info/LICENSE-3RD-PARTY
openfl_riscv-1.4.0.dev1.dist-info/METADATA
openfl_riscv-1.4.0.dev1.dist-info/NOTICE
openfl_riscv-1.4.0.dev1.dist-info/WHEEL
openfl_riscv-1.4.0.dev1.dist-info/entry_points.txt
openfl_riscv-1.4.0.dev1.dist-info/top_level.txt
openfl_riscv-1.4.0.dev1.dist-info/RECORD
