Metadata-Version: 2.1
Name: openfl-riscv
Version: 1.4.0.dev1
Summary: Federated Learning for the Edge RISC-V
Home-page: https://github.com/intel/openfl
Author: Intel Corporation - Gianluca Mittone
Project-URL: Bug Tracker, https://github.com/intel/openfl/issues
Project-URL: Documentation, https://openfl.readthedocs.io/en/stable/
Project-URL: Source Code, https://github.com/intel/openfl
Classifier: Environment :: Console
Classifier: Development Status :: 4 - Beta
Classifier: Intended Audience :: Developers
Classifier: Topic :: Scientific/Engineering :: Artificial Intelligence
Classifier: Topic :: Scientific/Engineering :: Image Recognition
Classifier: Topic :: System :: Distributed Computing
Classifier: License :: OSI Approved :: Apache Software License
Classifier: Programming Language :: Python :: 3
Classifier: Programming Language :: Python :: 3.6
Classifier: Programming Language :: Python :: 3.7
Classifier: Programming Language :: Python :: 3.8
Requires-Python: >=3.6, <3.9
License-File: LICENSE
License-File: LICENSE-3RD-PARTY
License-File: NOTICE
Requires-Dist: Click (==8.0.1)
Requires-Dist: cloudpickle (==2.1.0)
Requires-Dist: docker (==6.0.0)
Requires-Dist: dynaconf (==3.1.7)
Requires-Dist: flatten-json (==0.1.13)
Requires-Dist: ipykernel (==6.15.1)
Requires-Dist: pandas (==1.4.3)
Requires-Dist: protobuf (==3.19.4)
Requires-Dist: PyYAML (==6.0)
Requires-Dist: requests (==2.28.1)
Requires-Dist: rich (==9.1.0)
Requires-Dist: tensorboard (==2.10.0)
Requires-Dist: tensorboardX (==2.5.1)
Requires-Dist: tqdm (==4.64.0)
Requires-Dist: ninja (==1.10.2.3)
Requires-Dist: cffi (==1.15.1)
Requires-Dist: lxml (==4.9.1)
Requires-Dist: jupyterlab (==3.4.5)
Requires-Dist: grpcio (~=1.34.0)
Requires-Dist: scipy (==1.9.0)
Requires-Dist: scikit-learn (==1.1.2)
Requires-Dist: cryptography (==37.0.4)
